MatplotlibRumenjiaocheng/README.md
MatplotlibRumenjiaocheng/__init__.py
MatplotlibRumenjiaocheng/__main__.py
MatplotlibRumenjiaocheng/file.epub
MatplotlibRumenjiaocheng/index.html
MatplotlibRumenjiaocheng/css/__init__.py
MatplotlibRumenjiaocheng/css/annotations.css
MatplotlibRumenjiaocheng/css/main.css
MatplotlibRumenjiaocheng/css/normalize.css
MatplotlibRumenjiaocheng/css/popup.css
MatplotlibRumenjiaocheng/font/__init__.py
MatplotlibRumenjiaocheng/font/fontello.eot
MatplotlibRumenjiaocheng/font/fontello.svg
MatplotlibRumenjiaocheng/font/fontello.ttf
MatplotlibRumenjiaocheng/font/fontello.woff
MatplotlibRumenjiaocheng/img/__init__.py
MatplotlibRumenjiaocheng/img/annotator-glyph-sprite.png
MatplotlibRumenjiaocheng/img/annotator-icon-sprite.png
MatplotlibRumenjiaocheng/img/apple-touch-icon.png
MatplotlibRumenjiaocheng/img/cancelfullscreen.png
MatplotlibRumenjiaocheng/img/close.png
MatplotlibRumenjiaocheng/img/fullscreen.png
MatplotlibRumenjiaocheng/img/loader.gif
MatplotlibRumenjiaocheng/img/menu-icon.png
MatplotlibRumenjiaocheng/img/save.png
MatplotlibRumenjiaocheng/img/saved.png
MatplotlibRumenjiaocheng/img/settings-s.png
MatplotlibRumenjiaocheng/img/settings.png
MatplotlibRumenjiaocheng/img/star.png
MatplotlibRumenjiaocheng/js/__init__.py
MatplotlibRumenjiaocheng/js/epub.js
MatplotlibRumenjiaocheng/js/epub.min.js
MatplotlibRumenjiaocheng/js/epub.min.map
MatplotlibRumenjiaocheng/js/hooks.min.js
MatplotlibRumenjiaocheng/js/hooks.min.map
MatplotlibRumenjiaocheng/js/reader.js
MatplotlibRumenjiaocheng/js/reader.js.map
MatplotlibRumenjiaocheng/js/reader.min.js
MatplotlibRumenjiaocheng/js/reader.min.map
MatplotlibRumenjiaocheng/js/hooks/__init__.py
MatplotlibRumenjiaocheng/js/hooks/extensions/__init__.py
MatplotlibRumenjiaocheng/js/hooks/extensions/highlight.js
MatplotlibRumenjiaocheng/js/libs/__init__.py
MatplotlibRumenjiaocheng/js/libs/jquery.min.js
MatplotlibRumenjiaocheng/js/libs/localforage.min.js
MatplotlibRumenjiaocheng/js/libs/screenfull.js
matplotlib_rumenjiaocheng-2024.3.2.0.dist-info/METADATA
matplotlib_rumenjiaocheng-2024.3.2.0.dist-info/WHEEL
matplotlib_rumenjiaocheng-2024.3.2.0.dist-info/entry_points.txt
matplotlib_rumenjiaocheng-2024.3.2.0.dist-info/top_level.txt
matplotlib_rumenjiaocheng-2024.3.2.0.dist-info/RECORD
